hello_world_laura_y7860/__init__.py
hello_world_laura_y7860/tools/__init__.py
hello_world_laura_y7860/tools/hello_world_tool.py
hello_world_laura_y7860/tools/utils.py
hello_world_laura_y7860/yamls/hello_world_tool.yaml
tests/__init__.py
tests/test_hello_world_tool.py
hello_world_laura_y7860-0.0.1.dist-info/METADATA
hello_world_laura_y7860-0.0.1.dist-info/WHEEL
hello_world_laura_y7860-0.0.1.dist-info/entry_points.txt
hello_world_laura_y7860-0.0.1.dist-info/top_level.txt
hello_world_laura_y7860-0.0.1.dist-info/RECORD
